{
  "event": "CANGP26",
  "sport": "F1",
  "settled_at": "2026-06-02T14:42:00.851171+00:00",
  "race_winner": "Antonelli",
  "signals": [
    {
      "signal_id": "238345ba-7887-4b6d-a315-0922af88a997",
      "driver": "George Russell",
      "side": "BUY_NO",
      "source": "kalshi",
      "mid": 0.335,
      "stake": 5.0,
      "settled": true,
      "outcome": "won",
      "pnl_net": 9.9254,
      "finish_position": null
    },
    {
      "signal_id": "d3eb004c-16df-4a13-ac12-326d75fb12c6",
      "driver": "Lando Norris",
      "side": "BUY_YES",
      "source": "kalshi",
      "mid": 0.12,
      "stake": 5.0,
      "settled": true,
      "outcome": "lost",
      "pnl_net": -5.0,
      "finish_position": null
    },
    {
      "signal_id": "9c3ed3e4-dded-436f-b9a3-868c80389d3b",
      "driver": "Andrea Kimi Antonelli",
      "side": "BUY_NO",
      "source": "kalshi",
      "mid": 0.365,
      "stake": 5.0,
      "settled": true,
      "outcome": "lost",
      "pnl_net": -5.0,
      "finish_position": 1
    },
    {
      "signal_id": "64b15777-05f6-4ab3-882f-131fd06ce725",
      "driver": "George Russell",
      "side": "BUY_NO",
      "source": "kalshi",
      "mid": 0.335,
      "stake": 5.0,
      "settled": true,
      "outcome": "won",
      "pnl_net": 9.9254,
      "finish_position": null
    },
    {
      "signal_id": "7d224571-f62b-4162-bbb9-1f1b88f03b9a",
      "driver": "Lando Norris",
      "side": "BUY_YES",
      "source": "kalshi",
      "mid": 0.135,
      "stake": 5.0,
      "settled": true,
      "outcome": "lost",
      "pnl_net": -5.0,
      "finish_position": null
    },
    {
      "signal_id": "c2beefdc-494f-420b-8425-b96bc0516507",
      "driver": "Andrea Kimi Antonelli",
      "side": "BUY_NO",
      "source": "kalshi",
      "mid": 0.35,
      "stake": 5.0,
      "settled": true,
      "outcome": "lost",
      "pnl_net": -5.0,
      "finish_position": 1
    },
    {
      "signal_id": "7c77661e-33f3-48a5-b320-f14bba758c2d",
      "driver": "George Russell",
      "side": "BUY_NO",
      "source": "kalshi",
      "mid": 0.335,
      "stake": 5.0,
      "settled": true,
      "outcome": "won",
      "pnl_net": 9.9254,
      "finish_position": null
    },
    {
      "signal_id": "8ce227dd-4bdc-43a9-a057-e2b1105cc4c5",
      "driver": "Lando Norris",
      "side": "BUY_YES",
      "source": "kalshi",
      "mid": 0.125,
      "stake": 5.0,
      "settled": true,
      "outcome": "lost",
      "pnl_net": -5.0,
      "finish_position": null
    },
    {
      "signal_id": "8aa26b1a-b29e-4682-8bc0-ee8a0d020f05",
      "driver": "Andrea Kimi Antonelli",
      "side": "BUY_NO",
      "source": "kalshi",
      "mid": 0.39,
      "stake": 5.0,
      "settled": true,
      "outcome": "lost",
      "pnl_net": -5.0,
      "finish_position": 1
    },
    {
      "signal_id": "6db4b5dc-b9e1-46c6-ad58-d1c103be2cc7",
      "driver": "George Russell",
      "side": "BUY_NO",
      "source": "kalshi",
      "mid": 0.335,
      "stake": 5.0,
      "settled": true,
      "outcome": "won",
      "pnl_net": 9.9254,
      "finish_position": null
    },
    {
      "signal_id": "8a4e364f-6b0e-4289-957e-1badb5571553",
      "driver": "Lando Norris",
      "side": "BUY_YES",
      "source": "kalshi",
      "mid": 0.125,
      "stake": 5.0,
      "settled": true,
      "outcome": "lost",
      "pnl_net": -5.0,
      "finish_position": null
    },
    {
      "signal_id": "eaeeffc5-d000-4397-9531-5569f36fdce8",
      "driver": "Andrea Kimi Antonelli",
      "side": "BUY_NO",
      "source": "kalshi",
      "mid": 0.395,
      "stake": 5.0,
      "settled": true,
      "outcome": "lost",
      "pnl_net": -5.0,
      "finish_position": 1
    },
    {
      "signal_id": "7960a362-dce8-43f1-aa5c-e940e9abc335",
      "driver": "George Russell",
      "side": "BUY_NO",
      "source": "kalshi",
      "mid": 0.315,
      "stake": 5.0,
      "settled": true,
      "outcome": "won",
      "pnl_net": 10.873,
      "finish_position": null
    },
    {
      "signal_id": "cd89a536-154c-4bb8-99c4-1353c39d46d6",
      "driver": "Lando Norris",
      "side": "BUY_YES",
      "source": "kalshi",
      "mid": 0.115,
      "stake": 5.0,
      "settled": true,
      "outcome": "lost",
      "pnl_net": -5.0,
      "finish_position": null
    },
    {
      "signal_id": "f2affa8a-01b5-44e0-8722-8c7495e07f34",
      "driver": "Andrea Kimi Antonelli",
      "side": "BUY_NO",
      "source": "kalshi",
      "mid": 0.4,
      "stake": 5.0,
      "settled": true,
      "outcome": "lost",
      "pnl_net": -5.0,
      "finish_position": 1
    },
    {
      "signal_id": "0d3ca889-19f3-434b-9a04-200de792b532",
      "driver": "Max Verstappen",
      "side": "BUY_YES",
      "source": "kalshi",
      "mid": 0.09,
      "stake": 5.0,
      "settled": true,
      "outcome": "lost",
      "pnl_net": -5.0,
      "finish_position": null
    },
    {
      "signal_id": "2aa2f7e6-0c1e-4e2f-a6cc-08a6d55af1c8",
      "driver": "George Russell",
      "side": "BUY_NO",
      "source": "kalshi",
      "mid": 0.315,
      "stake": 5.0,
      "settled": true,
      "outcome": "won",
      "pnl_net": 10.873,
      "finish_position": null
    },
    {
      "signal_id": "8240909d-9a7d-4158-ab61-37373e148071",
      "driver": "Lando Norris",
      "side": "BUY_YES",
      "source": "kalshi",
      "mid": 0.125,
      "stake": 5.0,
      "settled": true,
      "outcome": "lost",
      "pnl_net": -5.0,
      "finish_position": null
    },
    {
      "signal_id": "6675e08d-1ef5-400c-bffb-797b6dcf6523",
      "driver": "Andrea Kimi Antonelli",
      "side": "BUY_NO",
      "source": "kalshi",
      "mid": 0.455,
      "stake": 5.0,
      "settled": true,
      "outcome": "lost",
      "pnl_net": -5.0,
      "finish_position": 1
    },
    {
      "signal_id": "2ff4b985-8bbe-4a56-8a02-43a3b17c252f",
      "driver": "Max Verstappen",
      "side": "BUY_YES",
      "source": "kalshi",
      "mid": 0.095,
      "stake": 5.0,
      "settled": true,
      "outcome": "lost",
      "pnl_net": -5.0,
      "finish_position": null
    },
    {
      "signal_id": "b98dc8ac-5c54-476c-a2ca-fa6af1451c41",
      "driver": "George Russell",
      "side": "BUY_NO",
      "source": "kalshi",
      "mid": 0.33,
      "stake": 5.0,
      "settled": true,
      "outcome": "won",
      "pnl_net": 10.1515,
      "finish_position": null
    },
    {
      "signal_id": "a7cec3d4-645e-4c53-a6dc-dd55b20a14b8",
      "driver": "Lando Norris",
      "side": "BUY_YES",
      "source": "kalshi",
      "mid": 0.13,
      "stake": 5.0,
      "settled": true,
      "outcome": "lost",
      "pnl_net": -5.0,
      "finish_position": null
    },
    {
      "signal_id": "3b653e1f-67eb-4124-b3e2-4b354cd4c8bd",
      "driver": "Andrea Kimi Antonelli",
      "side": "BUY_NO",
      "source": "kalshi",
      "mid": 0.445,
      "stake": 5.0,
      "settled": true,
      "outcome": "lost",
      "pnl_net": -5.0,
      "finish_position": 1
    },
    {
      "signal_id": "cfd289b6-a5b8-4be1-af6a-d1978ffc2371",
      "driver": "George Russell",
      "side": "BUY_NO",
      "source": "kalshi",
      "mid": 0.38,
      "stake": 5.0,
      "settled": true,
      "outcome": "won",
      "pnl_net": 8.1579,
      "finish_position": null
    },
    {
      "signal_id": "bf083c85-af43-4442-bcbf-cec428fd68f8",
      "driver": "Lando Norris",
      "side": "BUY_YES",
      "source": "kalshi",
      "mid": 0.105,
      "stake": 5.0,
      "settled": true,
      "outcome": "lost",
      "pnl_net": -5.0,
      "finish_position": null
    },
    {
      "signal_id": "2f0a5608-07dc-440c-94be-dc5ee3ca56b6",
      "driver": "Andrea Kimi Antonelli",
      "side": "BUY_NO",
      "source": "kalshi",
      "mid": 0.42,
      "stake": 5.0,
      "settled": true,
      "outcome": "lost",
      "pnl_net": -5.0,
      "finish_position": 1
    },
    {
      "signal_id": "671be192-d580-4fb9-864c-2570fc1794fa",
      "driver": "George Russell",
      "side": "BUY_NO",
      "source": "kalshi",
      "mid": 0.395,
      "stake": 5.0,
      "settled": true,
      "outcome": "won",
      "pnl_net": 7.6582,
      "finish_position": null
    },
    {
      "signal_id": "34cfbbee-fe87-4e3b-9743-89838a5caabd",
      "driver": "Lando Norris",
      "side": "BUY_YES",
      "source": "kalshi",
      "mid": 0.105,
      "stake": 5.0,
      "settled": true,
      "outcome": "lost",
      "pnl_net": -5.0,
      "finish_position": null
    },
    {
      "signal_id": "e85cab0b-336d-4134-995d-69e7cc010d45",
      "driver": "Andrea Kimi Antonelli",
      "side": "BUY_NO",
      "source": "kalshi",
      "mid": 0.405,
      "stake": 5.0,
      "settled": true,
      "outcome": "lost",
      "pnl_net": -5.0,
      "finish_position": 1
    },
    {
      "signal_id": "fcb5207a-1bc7-4e54-a976-ee21e74c1745",
      "driver": "George Russell",
      "side": "BUY_NO",
      "source": "kalshi",
      "mid": 0.395,
      "stake": 5.0,
      "settled": true,
      "outcome": "won",
      "pnl_net": 7.6582,
      "finish_position": null
    },
    {
      "signal_id": "33b61d9a-6132-4d63-86da-dd4e49bcf765",
      "driver": "Lando Norris",
      "side": "BUY_YES",
      "source": "kalshi",
      "mid": 0.105,
      "stake": 5.0,
      "settled": true,
      "outcome": "lost",
      "pnl_net": -5.0,
      "finish_position": null
    },
    {
      "signal_id": "bdfe9790-1e8a-4c8f-9cc6-bc87681af305",
      "driver": "Andrea Kimi Antonelli",
      "side": "BUY_NO",
      "source": "kalshi",
      "mid": 0.4,
      "stake": 5.0,
      "settled": true,
      "outcome": "lost",
      "pnl_net": -5.0,
      "finish_position": 1
    },
    {
      "signal_id": "090604ee-8f6f-424c-beb2-f343194dd952",
      "driver": "Andrea Kimi Antonelli",
      "side": "BUY_NO",
      "source": "kalshi",
      "mid": 0.375,
      "stake": 5.0,
      "settled": true,
      "outcome": "lost",
      "pnl_net": -5.0,
      "finish_position": 1
    },
    {
      "signal_id": "12e0b313-6574-48db-b159-b1d9ecf33948",
      "driver": "George Russell",
      "side": "BUY_NO",
      "source": "kalshi",
      "mid": 0.425,
      "stake": 5.0,
      "settled": true,
      "outcome": "won",
      "pnl_net": 6.7647,
      "finish_position": null
    },
    {
      "signal_id": "3a2e2c12-0783-4bb2-b277-402fbd08c1ca",
      "driver": "Lando Norris",
      "side": "BUY_YES",
      "source": "kalshi",
      "mid": 0.13,
      "stake": 5.0,
      "settled": true,
      "outcome": "lost",
      "pnl_net": -5.0,
      "finish_position": null
    },
    {
      "signal_id": "04e890a1-9dd4-4b2c-940d-538b5222bb8b",
      "driver": "George Russell",
      "side": "BUY_NO",
      "source": "kalshi",
      "mid": 0.38,
      "stake": 5.0,
      "settled": true,
      "outcome": "won",
      "pnl_net": 8.1579,
      "finish_position": null
    },
    {
      "signal_id": "00f58839-b015-4dc9-8c37-e5eac7cf72fc",
      "driver": "Andrea Kimi Antonelli",
      "side": "BUY_NO",
      "source": "kalshi",
      "mid": 0.445,
      "stake": 5.0,
      "settled": true,
      "outcome": "lost",
      "pnl_net": -5.0,
      "finish_position": 1
    },
    {
      "signal_id": "4c78ac9b-c3e6-4d0c-b5f7-393edf447f9c",
      "driver": "George Russell",
      "side": "BUY_NO",
      "source": "kalshi",
      "mid": 0.325,
      "stake": 5.0,
      "settled": true,
      "outcome": "won",
      "pnl_net": 10.3846,
      "finish_position": null
    },
    {
      "signal_id": "01743139-adcc-4b19-bc16-e97df661bf3c",
      "driver": "Andrea Kimi Antonelli",
      "side": "BUY_NO",
      "source": "kalshi",
      "mid": 0.475,
      "stake": 5.0,
      "settled": true,
      "outcome": "lost",
      "pnl_net": -5.0,
      "finish_position": 1
    },
    {
      "signal_id": "1142d29c-74db-475f-b922-912f49c4f9d9",
      "driver": "Isack Hadjar",
      "side": "BUY_NO",
      "source": "kalshi",
      "mid": 0.085,
      "stake": 5.0,
      "settled": true,
      "outcome": "won",
      "pnl_net": 53.8235,
      "finish_position": null
    },
    {
      "signal_id": "24149885-7fe6-47f1-8f60-b7516c0876eb",
      "driver": "Lando Norris",
      "side": "BUY_NO",
      "source": "kalshi",
      "mid": 0.27,
      "stake": 5.0,
      "settled": true,
      "outcome": "won",
      "pnl_net": 13.5185,
      "finish_position": null
    },
    {
      "signal_id": "8c52fa74-3e7a-4fe7-9195-17054f88c101",
      "driver": "George Russell",
      "side": "BUY_NO",
      "source": "kalshi",
      "mid": 0.485,
      "stake": 5.0,
      "settled": true,
      "outcome": "won",
      "pnl_net": 5.3093,
      "finish_position": null
    },
    {
      "signal_id": "695d8e49-dd55-4ba8-a737-d2646b8fbf4a",
      "driver": "Lando Norris",
      "side": "BUY_YES",
      "source": "kalshi",
      "mid": 0.095,
      "stake": 5.0,
      "settled": true,
      "outcome": "lost",
      "pnl_net": -5.0,
      "finish_position": null
    },
    {
      "signal_id": "0dbd188a-dea7-4be2-8f8c-2c698c4e0e26",
      "driver": "Andrea Kimi Antonelli",
      "side": "BUY_NO",
      "source": "kalshi",
      "mid": 0.315,
      "stake": 5.0,
      "settled": true,
      "outcome": "lost",
      "pnl_net": -5.0,
      "finish_position": 1
    },
    {
      "signal_id": "41332eba-da43-48f5-87b2-8a459a65287f",
      "driver": "Andrea Kimi Antonelli",
      "side": "BUY_NO",
      "source": "kalshi",
      "mid": 0.265,
      "stake": 5.0,
      "settled": true,
      "outcome": "lost",
      "pnl_net": -5.0,
      "finish_position": 1
    },
    {
      "signal_id": "e3e5e86c-8ae2-4c01-8a03-06c9431884f4",
      "driver": "Andrea Kimi Antonelli",
      "side": "BUY_NO",
      "source": "kalshi",
      "mid": 0.32,
      "stake": 5.0,
      "settled": true,
      "outcome": "lost",
      "pnl_net": -5.0,
      "finish_position": 1
    },
    {
      "signal_id": "3655e4fb-d26c-4108-9637-d7bfe94eda06",
      "driver": "George Russell",
      "side": "BUY_NO",
      "source": "kalshi",
      "mid": 0.445,
      "stake": 5.0,
      "settled": true,
      "outcome": "won",
      "pnl_net": 6.236,
      "finish_position": null
    }
  ],
  "summary": {
    "total": 47,
    "wins": 17,
    "losses": 30,
    "pnl_net": 49.2679
  }
}